<?xml version="1.0" encoding="UTF-8"?><artifacts>
    <artifact name="AdcMapping" groupId="com.example.InsisTP2.resource" version="1.0.0" type="registry/resource" serverRole="EnterpriseServiceBus">
        <item>
            <file>AdcMapping.dmc</file>
            <path>/_system/governance/datamapper</path>
            <mediaType>text/plain</mediaType>
        </item>
    </artifact>
    <artifact name="AdcMapping_inputSchema" groupId="com.example.InsisTP2.resource" version="1.0.0" type="registry/resource" serverRole="EnterpriseServiceBus">
        <item>
            <file>AdcMapping_inputSchema.json</file>
            <path>/_system/governance/datamapper</path>
            <mediaType>text/plain</mediaType>
        </item>
    </artifact>
    <artifact name="AdcMapping_outputSchema" groupId="com.example.InsisTP2.resource" version="1.0.0" type="registry/resource" serverRole="EnterpriseServiceBus">
        <item>
            <file>AdcMapping_outputSchema.json</file>
            <path>/_system/governance/datamapper</path>
            <mediaType>text/plain</mediaType>
        </item>
    </artifact>
    <artifact name="AdcMapping_xsltStyleSheet" groupId="com.example.InsisTP2.resource" version="1.0.0" type="registry/resource" serverRole="EnterpriseServiceBus">
        <item>
            <file>AdcMapping_xsltStyleSheet.xml</file>
            <path>/_system/governance/datamapper</path>
            <mediaType>text/plain</mediaType>
        </item>
    </artifact>
    <artifact name="ResponseMapping" groupId="com.example.InsisTP2.resource" version="1.0.0" type="registry/resource" serverRole="EnterpriseServiceBus">
        <item>
            <file>ResponseMapping.dmc</file>
            <path>/_system/governance/datamapper</path>
            <mediaType>text/plain</mediaType>
        </item>
    </artifact>
    <artifact name="ResponseMapping_inputSchema" groupId="com.example.InsisTP2.resource" version="1.0.0" type="registry/resource" serverRole="EnterpriseServiceBus">
        <item>
            <file>ResponseMapping_inputSchema.json</file>
            <path>/_system/governance/datamapper</path>
            <mediaType>text/plain</mediaType>
        </item>
    </artifact>
    <artifact name="ResponseMapping_outputSchema" groupId="com.example.InsisTP2.resource" version="1.0.0" type="registry/resource" serverRole="EnterpriseServiceBus">
        <item>
            <file>ResponseMapping_outputSchema.json</file>
            <path>/_system/governance/datamapper</path>
            <mediaType>text/plain</mediaType>
        </item>
    </artifact>
    <artifact name="ResponseMapping_xsltStyleSheet" groupId="com.example.InsisTP2.resource" version="1.0.0" type="registry/resource" serverRole="EnterpriseServiceBus">
        <item>
            <file>ResponseMapping_xsltStyleSheet.xml</file>
            <path>/_system/governance/datamapper</path>
            <mediaType>text/plain</mediaType>
        </item>
    </artifact>
    <artifact name="ResponseAdcMapping" groupId="com.example.InsisTP2.resource" version="1.0.0" type="registry/resource" serverRole="EnterpriseServiceBus">
        <item>
            <file>ResponseAdcMapping.dmc</file>
            <path>/_system/governance/datamapper</path>
            <mediaType>text/plain</mediaType>
        </item>
    </artifact>
    <artifact name="ResponseAdcMapping_inputSchema" groupId="com.example.InsisTP2.resource" version="1.0.0" type="registry/resource" serverRole="EnterpriseServiceBus">
        <item>
            <file>ResponseAdcMapping_inputSchema.json</file>
            <path>/_system/governance/datamapper</path>
            <mediaType>text/plain</mediaType>
        </item>
    </artifact>
    <artifact name="ResponseAdcMapping_outputSchema" groupId="com.example.InsisTP2.resource" version="1.0.0" type="registry/resource" serverRole="EnterpriseServiceBus">
        <item>
            <file>ResponseAdcMapping_outputSchema.json</file>
            <path>/_system/governance/datamapper</path>
            <mediaType>text/plain</mediaType>
        </item>
    </artifact>
    <artifact name="ResponseAdcMapping_xsltStyleSheet" groupId="com.example.InsisTP2.resource" version="1.0.0" type="registry/resource" serverRole="EnterpriseServiceBus">
        <item>
            <file>ResponseAdcMapping_xsltStyleSheet.xml</file>
            <path>/_system/governance/datamapper</path>
            <mediaType>text/plain</mediaType>
        </item>
    </artifact>
    <artifact name="JsonOutputObra" groupId="com.example.InsisTP2.resource" version="1.0.0" type="registry/resource" serverRole="EnterpriseServiceBus">
        <item>
            <file>JsonOutputObra.dmc</file>
            <path>/_system/governance/datamapper</path>
            <mediaType>text/plain</mediaType>
        </item>
    </artifact>
    <artifact name="JsonOutputObra_inputSchema" groupId="com.example.InsisTP2.resource" version="1.0.0" type="registry/resource" serverRole="EnterpriseServiceBus">
        <item>
            <file>JsonOutputObra_inputSchema.json</file>
            <path>/_system/governance/datamapper</path>
            <mediaType>text/plain</mediaType>
        </item>
    </artifact>
    <artifact name="JsonOutputObra_outputSchema" groupId="com.example.InsisTP2.resource" version="1.0.0" type="registry/resource" serverRole="EnterpriseServiceBus">
        <item>
            <file>JsonOutputObra_outputSchema.json</file>
            <path>/_system/governance/datamapper</path>
            <mediaType>text/plain</mediaType>
        </item>
    </artifact>
    <artifact name="JsonOutputObra_xsltStyleSheet" groupId="com.example.InsisTP2.resource" version="1.0.0" type="registry/resource" serverRole="EnterpriseServiceBus">
        <item>
            <file>JsonOutputObra_xsltStyleSheet.xml</file>
            <path>/_system/governance/datamapper</path>
            <mediaType>text/plain</mediaType>
        </item>
    </artifact>
    <artifact name="MapPoloXMLtoJSON" groupId="com.example.InsisTP2.resource" version="1.0.0" type="registry/resource" serverRole="EnterpriseServiceBus">
        <item>
            <file>MapPoloXMLtoJSON.dmc</file>
            <path>/_system/governance/datamapper</path>
            <mediaType>text/plain</mediaType>
        </item>
    </artifact>
    <artifact name="MapPoloXMLtoJSON_inputSchema" groupId="com.example.InsisTP2.resource" version="1.0.0" type="registry/resource" serverRole="EnterpriseServiceBus">
        <item>
            <file>MapPoloXMLtoJSON_inputSchema.json</file>
            <path>/_system/governance/datamapper</path>
            <mediaType>text/plain</mediaType>
        </item>
    </artifact>
    <artifact name="MapPoloXMLtoJSON_outputSchema" groupId="com.example.InsisTP2.resource" version="1.0.0" type="registry/resource" serverRole="EnterpriseServiceBus">
        <item>
            <file>MapPoloXMLtoJSON_outputSchema.json</file>
            <path>/_system/governance/datamapper</path>
            <mediaType>text/plain</mediaType>
        </item>
    </artifact>
    <artifact name="MapPoloXMLtoJSON_xsltStyleSheet" groupId="com.example.InsisTP2.resource" version="1.0.0" type="registry/resource" serverRole="EnterpriseServiceBus">
        <item>
            <file>MapPoloXMLtoJSON_xsltStyleSheet.xml</file>
            <path>/_system/governance/datamapper</path>
            <mediaType>text/plain</mediaType>
        </item>
    </artifact>
</artifacts>
